[
    {
        "title": "Home"
    },
    {
        "title": "Clothing"
    },
    {
        "title": "Clothing"
    },
    {
        "title": "Clothing"
    },
    {
        "title": "Garden"
    },
    {
        "title": "Baby"
    },
    {
        "title": "Kids"
    },
    {
        "title": "Beauty"
    },
    {
        "title": "Automotive"
    },
    {
        "title": "Beauty"
    },
    {
        "title": "Beauty"
    },
    {
        "title": "Health"
    },
    {
        "title": "Movies"
    },
    {
        "title": "Books"
    },
    {
        "title": "Movies"
    }
]